trackerlab/__init__.py
trackerlab/__main__.py
trackerlab/app.py
trackerlab/app.ui
trackerlab/app/__init__.py
trackerlab/app/app.py
trackerlab/app/app.ui
trackerlab/app/colormaps/Blue.csv
trackerlab/app/colormaps/Bone.csv
trackerlab/app/colormaps/Gray.csv
trackerlab/app/colormaps/Green.csv
trackerlab/app/colormaps/Hot.csv
trackerlab/app/colormaps/Jet.csv
trackerlab/app/colormaps/Red.csv
trackerlab/app/colormaps/Terrain.csv
trackerlab/app/colormaps/ThT 1.csv
trackerlab/app/colormaps/ThT 2.csv
trackerlab/app/colormaps/Viridis.csv
trackerlab/app/colormaps/White-Blue.csv
trackerlab/app/ffmpeg/ffmpeg.exe
trackerlab/app/modules/__init__.py
trackerlab/app/modules/connected_component/__init__.py
trackerlab/app/modules/connected_component/connected_component.py
trackerlab/app/modules/utils/__init__.py
trackerlab/app/modules/utils/helpwidget.py
trackerlab/app/modules/utils/pgutils.py
trackerlab/app/modules/utils/settings.py
trackerlab/detectors/__init__.py
trackerlab/detectors/blob_detection.py
trackerlab/detectors/connected_components.py
trackerlab/detectors/hough_transform.py
trackerlab/readers/__init__.py
trackerlab/readers/readers.py
trackerlab/utils/__init__.py
trackerlab/utils/utils.py
trackerlab-0.0.5.dist-info/LICENSE
trackerlab-0.0.5.dist-info/METADATA
trackerlab-0.0.5.dist-info/WHEEL
trackerlab-0.0.5.dist-info/top_level.txt
trackerlab-0.0.5.dist-info/RECORD
