Metadata-Version: 2.1
Name: trackerlab
Version: 0.0.5
Summary: Package for detecting features in digital microscopy images
Home-page: https://github.com/fraem24/TrackerLab
Author: Martin
Author-email: martin.fraenzl@physik.uni-leipzig.de
License: UNKNOWN
Platform: UNKNOWN
Classifier: Programming Language :: Python :: 3
Classifier: License :: OSI Approved :: MIT License
Classifier: Operating System :: OS Independent
Requires-Dist: nptdms (>=1.1.0)
Requires-Dist: pyqtgraph (==0.11.0)
